warmac/__init__.py
warmac/__main__.py
warmac/warmac_average.py
warmac/warmac_errors.py
warmac/warmac_parser.py
warmac-0.0.4.dist-info/entry_points.txt
warmac-0.0.4.dist-info/LICENSE.txt
warmac-0.0.4.dist-info/METADATA
warmac-0.0.4.dist-info/WHEEL
warmac-0.0.4.dist-info/RECORD
