Metadata-Version: 2.1
Name: WarMAC
Version: 0.0.4
Summary: An average platinum price calculator for tradeable items in Warframe.
Home-page: https://github.com/Eutropios/WarMAC
License: MIT
Keywords: platinum,warframe calculator,warframe market,warframe
Author: Noah Jenner
Author-email: noah.jenner@proton.me
Maintainer: Noah Jenner
Maintainer-email: noah.jenner@proton.me
Requires-Python: >=3.8,<3.13.0
Classifier: Development Status :: 4 - Beta
Classifier: Environment :: Console
Classifier: Intended Audience :: End Users/Desktop
Classifier: License :: OSI Approved :: MIT License
Classifier: Operating System :: OS Independent
Classifier: Programming Language :: Python :: 3
Classifier: Programming Language :: Python :: 3.8
Classifier: Programming Language :: Python :: 3.9
Classifier: Programming Language :: Python :: 3.10
Classifier: Programming Language :: Python :: 3.11
Classifier: Programming Language :: Python :: 3.12
Classifier: Programming Language :: Python :: Implementation :: CPython
Classifier: Topic :: Utilities
Classifier: Typing :: Typed
Requires-Dist: urllib3 (>=2.0.4,<3.0.0)
Project-URL: Bug Tracker, https://github.com/Eutropios/WarMAC/issues
Project-URL: Documentation, https://warmac.readthedocs.io/en/
Project-URL: Repository, https://github.com/Eutropios/WarMAC
